cookiefarm_exploiter/__init__.py
cookiefarm_exploiter/exploiter_manager.py
cookiefarm_exploiter/logger.py
cookiefarm_exploiter-0.0.15.dist-info/METADATA
cookiefarm_exploiter-0.0.15.dist-info/WHEEL
cookiefarm_exploiter-0.0.15.dist-info/licenses/LICENSE
cookiefarm_exploiter-0.0.15.dist-info/RECORD
